arpa2.reservoir-0.2.0-py3.7-nspkg.pth
arpa2/reservoir/__init__.py
arpa2/reservoir/api.py
arpa2/reservoir/rmt.py
arpa2/reservoir/sftp.py
arpa2/reservoir/shell.py
arpa2.reservoir-0.2.0.dist-info/METADATA
arpa2.reservoir-0.2.0.dist-info/WHEEL
arpa2.reservoir-0.2.0.dist-info/entry_points.txt
arpa2.reservoir-0.2.0.dist-info/namespace_packages.txt
arpa2.reservoir-0.2.0.dist-info/top_level.txt
arpa2.reservoir-0.2.0.dist-info/RECORD
