Metadata-Version: 2.1
Name: arpa2.reservoir
Version: 0.2.0
Summary: ARPA2 Reservoir -- object store with metadata in LDAP
Home-page: https://github.com/arpa2/reservoir
Author: Rick van Rein (for the ARPA2 Reservoir project)
Author-email: rick@openfortress.nl
License: UNKNOWN
Platform: UNKNOWN
Requires-Dist: arpa2.shell
Requires-Dist: python-ldap
Requires-Dist: gssapi
Requires-Dist: six
Requires-Dist: enum34 ; python_version < "3"
